psd2fabric/__init__.py
psd2fabric/psd_fabric.py
psd2fabric/fabric/__init__.py
psd2fabric/fabric/group.py
psd2fabric/fabric/image.py
psd2fabric/fabric/text.py
psd2fabric/parser/__init__.py
psd2fabric/parser/group_parser.py
psd2fabric/parser/image_parser.py
psd2fabric/parser/psd_parser.py
psd2fabric/parser/type_parser.py
psd2fabric/parser/effects/__init__.py
psd2fabric/parser/effects/coloroverlay_parser.py
psd2fabric/parser/effects/stroke_parser.py
psd2fabric/render/__init__.py
psd2fabric/render/json_render.py
psd2fabric-0.5.1.dist-info/METADATA
psd2fabric-0.5.1.dist-info/WHEEL
psd2fabric-0.5.1.dist-info/entry_points.txt
psd2fabric-0.5.1.dist-info/top_level.txt
psd2fabric-0.5.1.dist-info/RECORD
