Metadata-Version: 2.1
Name: psd2fabric
Version: 0.5.1
Requires-Dist: psd-tools ==1.9.28
